[
{"korean": "하나", "english": "one (native)"},
{"korean": "둘", "english": "two (native)"},
{"korean": "셋", "english": "three (native)"},
{"korean": "넷", "english": "four (native)"},
{"korean": "다섯", "english": "five (native)"},
{"korean": "여섯", "english": "six (native)"},
{"korean": "일곱", "english": "seven (native)"},
{"korean": "여덟", "english": "eight (native)"},
{"korean": "아홉", "english": "nine (native)"},
{"korean": "열", "english": "ten (native)"},
{"korean": "열하나", "english": "eleven (native)"},
{"korean": "열둘", "english": "twelve (native)"},
{"korean": "열셋", "english": "thirteen (native)"},
{"korean": "열넷", "english": "fourteen (native)"},
{"korean": "열다섯", "english": "fifteen (native)"},
{"korean": "열여섯", "english": "sixteen (native)"},
{"korean": "열일곱", "english": "seventeen (native)"},
{"korean": "열여덟", "english": "eighteen (native)"},
{"korean": "열아홉", "english": "nineteen (native)"},
{"korean": "스물", "english": "twenty (native)"},
{"korean": "스물하나", "english": "twenty-one (native)"},
{"korean": "스물둘", "english": "twenty-two (native)"},
{"korean": "스물셋", "english": "twenty-three (native)"},
{"korean": "스물넷", "english": "twenty-four (native)"},
{"korean": "스물다섯", "english": "twenty-five (native)"},
{"korean": "스물여섯", "english": "twenty-six (native)"},
{"korean": "스물일곱", "english": "twenty-seven (native)"},
{"korean": "스물여덟", "english": "twenty-eight (native)"},
{"korean": "스물아홉", "english": "twenty-nine (native)"},
{"korean": "서른", "english": "thirty (native)"}
]
